{
  "voc_eval_res": {
    "precision": 77.1144,
    "recall": 61.8762,
    "f-score": 68.66
  },
  "KL_res": {
    "KL divergence": 0.7842311108038463,
    "Euclidean Dist.": 0.04388676395741401,
    "WER": 0.43431952662721895,
    "CER": 0.32709020077914297,
    "Cosine Dist.": 0.04946222340187567
  },
  "occ_eval_res": {
    "precision": 79.8319,
    "recall": 67.4556,
    "f-score": 73.1238
  },
  "clean_eval": {
    "f-score": 63.73770491803279,
    "precision": 58.6248492159228,
    "recall": 69.82758620689656,
    "tp": 486,
    "fp": 343,
    "fn": 210
  },
  "jaccard": [
    0.3237410071942446
  ],
  "braycurtis": [
    0.12604848018468642
  ],
  "dice": [
    0.19313304721030042
  ],
  "cosinus": [
    0.013280236602566498
  ]
}