{
  "spacy-lg-3.7.5_kraken4.3.13.dev25": {
    "EN-occ": 3116,
    "EN-type": 2314
  },
  "spacy-lg-3.7.5_lectaurep-kraken4.3.13.dev25": {
    "EN-occ": 3610,
    "EN-type": 2962
  },
  "spacy-lg-3.7.5_tesseract0.3.10": {
    "EN-occ": 1913,
    "EN-type": 682
  },
  "spacy-lg-3.7.5_Ref": {
    "EN-occ": 731,
    "EN-type": 261
  },
  "spacy-md-3.7.5_kraken4.3.13.dev25": {
    "EN-occ": 3116,
    "EN-type": 2314
  },
  "spacy-md-3.7.5_lectaurep-kraken4.3.13.dev25": {
    "EN-occ": 3610,
    "EN-type": 2962
  },
  "spacy-md-3.7.5_tesseract0.3.10": {
    "EN-occ": 1913,
    "EN-type": 682
  },
  "spacy-md-3.7.5_Ref": {
    "EN-occ": 731,
    "EN-type": 261
  },
  "spacy-sm-3.7.5_kraken4.3.13.dev25": {
    "EN-occ": 3116,
    "EN-type": 2314
  },
  "spacy-sm-3.7.5_lectaurep-kraken4.3.13.dev25": {
    "EN-occ": 3610,
    "EN-type": 2962
  },
  "spacy-sm-3.7.5_tesseract0.3.10": {
    "EN-occ": 1913,
    "EN-type": 682
  },
  "spacy-sm-3.7.5_Ref": {
    "EN-occ": 731,
    "EN-type": 261
  }
}