{
  "entite_0": {
    "label": "LOC",
    "text": "Bibliothèque nationale de France",
    "jalons": [
      57,
      89
    ]
  },
  "entite_1": {
    "label": "ORG",
    "text": "Gallica\n\n \n\nÎ",
    "jalons": [
      95,
      108
    ]
  },
  "entite_2": {
    "label": "ORG",
    "text": "Gallica",
    "jalons": [
      176,
      183
    ]
  },
  "entite_3": {
    "label": "MISC",
    "text": "BnF. Leur",
    "jalons": [
      307,
      316
    ]
  },
  "entite_4": {
    "label": "MISC",
    "text": "Source gallica.bnf.fr",
    "jalons": [
      670,
      691
    ]
  },
  "entite_5": {
    "label": "LOC",
    "text": "Bibliothèque nationale",
    "jalons": [
      694,
      716
    ]
  },
  "entite_6": {
    "label": "LOC",
    "text": "de France",
    "jalons": [
      717,
      726
    ]
  },
  "entite_7": {
    "label": "MISC",
    "text": "« Source gallica.bnf.fr",
    "jalons": [
      732,
      755
    ]
  },
  "entite_8": {
    "label": "MISC",
    "text": "BnF »",
    "jalons": [
      758,
      763
    ]
  },
  "entite_9": {
    "label": "ORG",
    "text": "ACCÉDER",
    "jalons": [
      1276,
      1283
    ]
  },
  "entite_10": {
    "label": "ORG",
    "text": "TARIFS",
    "jalons": [
      1288,
      1294
    ]
  },
  "entite_11": {
    "label": "MISC",
    "text": "BnF",
    "jalons": [
      1366,
      1369
    ]
  },
  "entite_12": {
    "label": "ORG",
    "text": "Source gallica.BnF.fr",
    "jalons": [
      1910,
      1931
    ]
  },
  "entite_13": {
    "label": "LOC",
    "text": "Bibliothèque",
    "jalons": [
      1934,
      1946
    ]
  },
  "entite_14": {
    "label": "ORG",
    "text": "Gallica",
    "jalons": [
      2094,
      2101
    ]
  },
  "entite_15": {
    "label": "MISC",
    "text": "BnF",
    "jalons": [
      2141,
      2144
    ]
  },
  "entite_16": {
    "label": "MISC",
    "text": "L341",
    "jalons": [
      2194,
      2198
    ]
  },
  "entite_17": {
    "label": "LOC",
    "text": "Gallica",
    "jalons": [
      2312,
      2319
    ]
  },
  "entite_18": {
    "label": "ORG",
    "text": "Gallica",
    "jalons": [
      2823,
      2830
    ]
  },
  "entite_19": {
    "label": "LOC",
    "text": "utilisation.commerciale@ bnf.fr",
    "jalons": [
      2862,
      2893
    ]
  },
  "entite_20": {
    "label": "MISC",
    "text": "JÉknesset",
    "jalons": [
      2941,
      2950
    ]
  },
  "entite_21": {
    "label": "LOC",
    "text": "|",
    "jalons": [
      2982,
      2983
    ]
  },
  "entite_22": {
    "label": "ORG",
    "text": "Jeunesse 3",
    "jalons": [
      3158,
      3168
    ]
  },
  "entite_23": {
    "label": "PER",
    "text": "Plutus",
    "jalons": [
      3175,
      3181
    ]
  },
  "entite_24": {
    "label": "LOC",
    "text": "Biens",
    "jalons": [
      3186,
      3191
    ]
  },
  "entite_25": {
    "label": "ORG",
    "text": "& Pallas",
    "jalons": [
      3193,
      3201
    ]
  },
  "entite_26": {
    "label": "LOC",
    "text": "Sagele",
    "jalons": [
      3205,
      3211
    ]
  },
  "entite_27": {
    "label": "LOC",
    "text": "Honneurs",
    "jalons": [
      3232,
      3240
    ]
  },
  "entite_28": {
    "label": "LOC",
    "text": "& Venus",
    "jalons": [
      3243,
      3250
    ]
  },
  "entite_29": {
    "label": "MISC",
    "text": "V'vertus qu’",
    "jalons": [
      3319,
      3331
    ]
  },
  "entite_30": {
    "label": "MISC",
    "text": "Vous :\n\nMais l'Hymen",
    "jalons": [
      3347,
      3367
    ]
  },
  "entite_31": {
    "label": "MISC",
    "text": "Victoire",
    "jalons": [
      3390,
      3398
    ]
  },
  "entite_32": {
    "label": "LOC",
    "text": "Epoux",
    "jalons": [
      3443,
      3448
    ]
  },
  "entite_33": {
    "label": "MISC",
    "text": "RG EE",
    "jalons": [
      3475,
      3480
    ]
  },
  "entite_34": {
    "label": "ORG",
    "text": "EEE",
    "jalons": [
      3488,
      3491
    ]
  },
  "entite_35": {
    "label": "MISC",
    "text": "Portrait de Mademoiselle + X",
    "jalons": [
      3521,
      3549
    ]
  },
  "entite_36": {
    "label": "PER",
    "text": "fon Pinçeau",
    "jalons": [
      3566,
      3577
    ]
  },
  "entite_37": {
    "label": "MISC",
    "text": "Portrait",
    "jalons": [
      3647,
      3655
    ]
  },
  "entite_38": {
    "label": "LOC",
    "text": "Modele",
    "jalons": [
      3678,
      3684
    ]
  },
  "entite_39": {
    "label": "LOC",
    "text": "E",
    "jalons": [
      3712,
      3713
    ]
  },
  "entite_40": {
    "label": "LOC",
    "text": "|",
    "jalons": [
      3715,
      3716
    ]
  },
  "entite_41": {
    "label": "LOC",
    "text": "Kk 2",
    "jalons": [
      3763,
      3767
    ]
  },
  "entite_42": {
    "label": "LOC",
    "text": "Retour",
    "jalons": [
      3778,
      3784
    ]
  },
  "entite_43": {
    "label": "LOC",
    "text": "Paris",
    "jalons": [
      3787,
      3792
    ]
  },
  "entite_44": {
    "label": "ORG",
    "text": "MADRID AL",
    "jalons": [
      3797,
      3806
    ]
  },
  "entite_45": {
    "label": "MISC",
    "text": "E Printemps & PEté",
    "jalons": [
      3808,
      3826
    ]
  },
  "entite_46": {
    "label": "ORG",
    "text": "Saisons |",
    "jalons": [
      3842,
      3851
    ]
  },
  "entite_47": {
    "label": "PER",
    "text": "Moiflons",
    "jalons": [
      3910,
      3918
    ]
  },
  "entite_48": {
    "label": "MISC",
    "text": "Fleurs",
    "jalons": [
      3943,
      3949
    ]
  },
  "entite_49": {
    "label": "MISC",
    "text": "Partage",
    "jalons": [
      3968,
      3975
    ]
  },
  "entite_50": {
    "label": "MISC",
    "text": "Dons précieux",
    "jalons": [
      3998,
      4011
    ]
  },
  "entite_51": {
    "label": "LOC",
    "text": "Balance",
    "jalons": [
      4052,
      4059
    ]
  },
  "entite_52": {
    "label": "PER",
    "text": "Puisqu",
    "jalons": [
      4065,
      4071
    ]
  },
  "entite_53": {
    "label": "MISC",
    "text": "Plaisirs & les Jeux",
    "jalons": [
      4091,
      4110
    ]
  },
  "entite_54": {
    "label": "MISC",
    "text": "Presence",
    "jalons": [
      4137,
      4145
    ]
  },
  "entite_55": {
    "label": "MISC",
    "text": "EEEAEER",
    "jalons": [
      4167,
      4174
    ]
  },
  "entite_56": {
    "label": "LOC",
    "text": "L A. MESM_E.",
    "jalons": [
      4180,
      4192
    ]
  },
  "entite_57": {
    "label": "PER",
    "text": "MADRIL",
    "jalons": [
      4193,
      4199
    ]
  },
  "entite_58": {
    "label": "MISC",
    "text": "Cœur",
    "jalons": [
      4417,
      4421
    ]
  },
  "entite_59": {
    "label": "MISC",
    "text": "MESME",
    "jalons": [
      4494,
      4499
    ]
  },
  "entite_60": {
    "label": "LOC",
    "text": "U",
    "jalons": [
      4513,
      4514
    ]
  },
  "entite_61": {
    "label": "LOC",
    "text": "Donnons",
    "jalons": [
      4603,
      4610
    ]
  },
  "entite_62": {
    "label": "LOC",
    "text": "Baisers",
    "jalons": [
      4639,
      4646
    ]
  },
  "entite_63": {
    "label": "LOC",
    "text": "Etrennes",
    "jalons": [
      4656,
      4664
    ]
  },
  "entite_64": {
    "label": "LOC",
    "text": "annnnseennnaDEs",
    "jalons": [
      4671,
      4686
    ]
  },
  "entite_65": {
    "label": "LOC",
    "text": "|",
    "jalons": [
      4706,
      4707
    ]
  },
  "entite_66": {
    "label": "LOC",
    "text": "A MADAME**.",
    "jalons": [
      4712,
      4723
    ]
  },
  "entite_67": {
    "label": "ORG",
    "text": "BOUQUET",
    "jalons": [
      4726,
      4733
    ]
  },
  "entite_68": {
    "label": "PER",
    "text": "E Devoir",
    "jalons": [
      4736,
      4744
    ]
  },
  "entite_69": {
    "label": "MISC",
    "text": "AMitié",
    "jalons": [
      4746,
      4752
    ]
  },
  "entite_70": {
    "label": "MISC",
    "text": "Amour & l’'Interêt",
    "jalons": [
      4757,
      4775
    ]
  },
  "entite_71": {
    "label": "MISC",
    "text": "Motifs",
    "jalons": [
      4787,
      4793
    ]
  },
  "entite_72": {
    "label": "LOC",
    "text": "Usage",
    "jalons": [
      4808,
      4813
    ]
  },
  "entite_73": {
    "label": "MISC",
    "text": "IMprudent",
    "jalons": [
      4822,
      4831
    ]
  },
  "entite_74": {
    "label": "MISC",
    "text": "toujours.|",
    "jalons": [
      4853,
      4863
    ]
  },
  "entite_75": {
    "label": "LOC",
    "text": "|",
    "jalons": [
      4887,
      4888
    ]
  },
  "entite_76": {
    "label": "PER",
    "text": "Bouquet",
    "jalons": [
      4921,
      4928
    ]
  },
  "entite_77": {
    "label": "PER",
    "text": "Recevez",
    "jalons": [
      4931,
      4938
    ]
  },
  "entite_78": {
    "label": "MISC",
    "text": "Gage\n\n",
    "jalons": [
      4963,
      4969
    ]
  },
  "entite_79": {
    "label": "MISC",
    "text": "Discours",
    "jalons": [
      5066,
      5074
    ]
  },
  "entite_80": {
    "label": "MISC",
    "text": "Le Cœur seul l’",
    "jalons": [
      5100,
      5115
    ]
  },
  "entite_81": {
    "label": "MISC",
    "text": "S’",
    "jalons": [
      5152,
      5154
    ]
  },
  "entite_82": {
    "label": "MISC",
    "text": "naufrage >\n\nJe suis content",
    "jalons": [
      5175,
      5202
    ]
  },
  "entite_83": {
    "label": "MISC",
    "text": "|\n\nSR GER hs",
    "jalons": [
      5221,
      5233
    ]
  },
  "entite_84": {
    "label": "PER",
    "text": "L.\n\n",
    "jalons": [
      5279,
      5283
    ]
  },
  "entite_85": {
    "label": "LOC",
    "text": "Est",
    "jalons": [
      5351,
      5354
    ]
  },
  "entite_86": {
    "label": "PER",
    "text": "Rà",
    "jalons": [
      5363,
      5365
    ]
  },
  "entite_87": {
    "label": "MISC",
    "text": "Cœur tendre & fidele",
    "jalons": [
      5423,
      5443
    ]
  },
  "entite_88": {
    "label": "MISC",
    "text": "MADEMOISELLE",
    "jalons": [
      5506,
      5518
    ]
  },
  "entite_89": {
    "label": "MISC",
    "text": "MADRIL",
    "jalons": [
      5523,
      5529
    ]
  },
  "entite_90": {
    "label": "LOC",
    "text": "Main",
    "jalons": [
      5554,
      5558
    ]
  },
  "entite_91": {
    "label": "MISC",
    "text": "Pinçeau",
    "jalons": [
      5594,
      5601
    ]
  },
  "entite_92": {
    "label": "MISC",
    "text": "Peintre",
    "jalons": [
      5615,
      5622
    ]
  },
  "entite_93": {
    "label": "MISC",
    "text": "Tableau 5",
    "jalons": [
      5643,
      5652
    ]
  },
  "entite_94": {
    "label": "PER",
    "text": "Rendre la Peinture",
    "jalons": [
      5653,
      5671
    ]
  },
  "entite_95": {
    "label": "LOC",
    "text": "Ai}\n\f\n \n\nA Mais",
    "jalons": [
      5679,
      5694
    ]
  },
  "entite_96": {
    "label": "ORG",
    "text": "Elé",
    "jalons": [
      5708,
      5711
    ]
  },
  "entite_97": {
    "label": "MISC",
    "text": "E Dieu",
    "jalons": [
      5733,
      5739
    ]
  },
  "entite_98": {
    "label": "LOC",
    "text": "|",
    "jalons": [
      5777,
      5778
    ]
  },
  "entite_99": {
    "label": "ORG",
    "text": "DESSUS",
    "jalons": [
      5871,
      5877
    ]
  },
  "entite_100": {
    "label": "MISC",
    "text": "MARTIAL",
    "jalons": [
      5896,
      5903
    ]
  },
  "entite_101": {
    "label": "MISC",
    "text": "Nom",
    "jalons": [
      6003,
      6006
    ]
  },
  "entite_102": {
    "label": "LOC",
    "text": "Nom de Sympathie",
    "jalons": [
      6052,
      6068
    ]
  },
  "entite_103": {
    "label": "MISC",
    "text": "Je soupire",
    "jalons": [
      6140,
      6150
    ]
  },
  "entite_104": {
    "label": "MISC",
    "text": "»",
    "jalons": [
      6205,
      6206
    ]
  },
  "entite_105": {
    "label": "MISC",
    "text": "La R",
    "jalons": [
      6218,
      6222
    ]
  },
  "entite_106": {
    "label": "MISC",
    "text": "LA M E ME",
    "jalons": [
      6247,
      6256
    ]
  },
  "entite_107": {
    "label": "MISC",
    "text": "Maladie",
    "jalons": [
      6274,
      6281
    ]
  },
  "entite_108": {
    "label": "MISC",
    "text": "Malheurs",
    "jalons": [
      6314,
      6322
    ]
  },
  "entite_109": {
    "label": "MISC",
    "text": "Pleurs 3",
    "jalons": [
      6358,
      6366
    ]
  },
  "entite_110": {
    "label": "LOC",
    "text": "|",
    "jalons": [
      6415,
      6416
    ]
  },
  "entite_111": {
    "label": "MISC",
    "text": "Presence",
    "jalons": [
      6497,
      6505
    ]
  },
  "entite_112": {
    "label": "PER",
    "text": "Modifiera",
    "jalons": [
      6508,
      6517
    ]
  },
  "entite_113": {
    "label": "LOC",
    "text": "MADRIL\n\nViens",
    "jalons": [
      6619,
      6632
    ]
  },
  "entite_114": {
    "label": "ORG",
    "text": "Elé",
    "jalons": [
      6644,
      6647
    ]
  },
  "entite_115": {
    "label": "MISC",
    "text": "Querelle : :",
    "jalons": [
      6706,
      6718
    ]
  },
  "entite_116": {
    "label": "MISC",
    "text": "Toy:moy'",
    "jalons": [
      6724,
      6732
    ]
  },
  "entite_117": {
    "label": "PER",
    "text": "Amour",
    "jalons": [
      6743,
      6748
    ]
  },
  "entite_118": {
    "label": "MISC",
    "text": "LE Re Loic",
    "jalons": [
      7023,
      7033
    ]
  },
  "entite_119": {
    "label": "MISC",
    "text": "L A MESME",
    "jalons": [
      7045,
      7054
    ]
  },
  "entite_120": {
    "label": "MISC",
    "text": "MADRIL",
    "jalons": [
      7056,
      7062
    ]
  },
  "entite_121": {
    "label": "PER",
    "text": "Divin Objet",
    "jalons": [
      7099,
      7110
    ]
  },
  "entite_122": {
    "label": "LOC",
    "text": "Eh",
    "jalons": [
      7125,
      7127
    ]
  },
  "entite_123": {
    "label": "PER",
    "text": "Implorer d'Apollon",
    "jalons": [
      7163,
      7181
    ]
  },
  "entite_124": {
    "label": "MISC",
    "text": "Ah !",
    "jalons": [
      7205,
      7209
    ]
  },
  "entite_125": {
    "label": "LOC",
    "text": "Aurais",
    "jalons": [
      7248,
      7254
    ]
  },
  "entite_126": {
    "label": "PER",
    "text": "Discours",
    "jalons": [
      7268,
      7276
    ]
  },
  "entite_127": {
    "label": "MISC",
    "text": "L A MESM E",
    "jalons": [
      7330,
      7340
    ]
  },
  "entite_128": {
    "label": "MISC",
    "text": "MADRIL",
    "jalons": [
      7342,
      7348
    ]
  },
  "entite_129": {
    "label": "MISC",
    "text": "À Pres",
    "jalons": [
      7351,
      7357
    ]
  },
  "entite_130": {
    "label": "ORG",
    "text": "Ê& Gardé",
    "jalons": [
      7381,
      7389
    ]
  },
  "entite_131": {
    "label": "MISC",
    "text": "Cœur de l'Enfant de Thermes",
    "jalons": [
      7394,
      7421
    ]
  },
  "entite_132": {
    "label": "MISC",
    "text": "Dieu",
    "jalons": [
      7438,
      7442
    ]
  },
  "entite_133": {
    "label": "MISC",
    "text": "Mortel",
    "jalons": [
      7499,
      7505
    ]
  },
  "entite_134": {
    "label": "PER",
    "text": "Changeons",
    "jalons": [
      7579,
      7588
    ]
  },
  "entite_135": {
    "label": "LOC",
    "text": "Suffi",
    "jalons": [
      7639,
      7644
    ]
  },
  "entite_136": {
    "label": "MISC",
    "text": "Cœur\n\nJe fentes des effets de fà toute- puissance",
    "jalons": [
      7658,
      7707
    ]
  },
  "entite_137": {
    "label": "PER",
    "text": "Roy des Dieux",
    "jalons": [
      7713,
      7726
    ]
  },
  "entite_138": {
    "label": "LOC",
    "text": "Eh",
    "jalons": [
      7768,
      7770
    ]
  },
  "entite_139": {
    "label": "MISC",
    "text": "RE\n\n",
    "jalons": [
      7865,
      7869
    ]
  },
  "entite_140": {
    "label": "MISC",
    "text": "ALlEz",
    "jalons": [
      7896,
      7901
    ]
  },
  "entite_141": {
    "label": "ORG",
    "text": "Elé",
    "jalons": [
      7913,
      7916
    ]
  },
  "entite_142": {
    "label": "PER",
    "text": "Renom",
    "jalons": [
      7981,
      7986
    ]
  },
  "entite_143": {
    "label": "ORG",
    "text": "Patron\n\n",
    "jalons": [
      8026,
      8034
    ]
  },
  "entite_144": {
    "label": "PER",
    "text": "Vos Emplois",
    "jalons": [
      8075,
      8086
    ]
  },
  "entite_145": {
    "label": "LOC",
    "text": "Fideles",
    "jalons": [
      8142,
      8149
    ]
  },
  "entite_146": {
    "label": "LOC",
    "text": "Belles",
    "jalons": [
      8198,
      8204
    ]
  },
  "entite_147": {
    "label": "LOC",
    "text": "Amans",
    "jalons": [
      8236,
      8241
    ]
  },
  "entite_148": {
    "label": "LOC",
    "text": "Miracles",
    "jalons": [
      8313,
      8321
    ]
  },
  "entite_149": {
    "label": "LOC",
    "text": "Elûs",
    "jalons": [
      8344,
      8348
    ]
  },
  "entite_150": {
    "label": "LOC",
    "text": "Lieu",
    "jalons": [
      8365,
      8369
    ]
  },
  "entite_151": {
    "label": "LOC",
    "text": "Empire d'Amour",
    "jalons": [
      8376,
      8390
    ]
  },
  "entite_152": {
    "label": "MISC",
    "text": "Limites",
    "jalons": [
      8404,
      8411
    ]
  },
  "entite_153": {
    "label": "PER",
    "text": "Profiteurs",
    "jalons": [
      8432,
      8442
    ]
  },
  "entite_154": {
    "label": "MISC",
    "text": "Mes",
    "jalons": [
      8459,
      8462
    ]
  },
  "entite_155": {
    "label": "MISC",
    "text": "D'1E u.\n\n",
    "jalons": [
      8465,
      8474
    ]
  },
  "entite_156": {
    "label": "PER",
    "text": "MADRIL",
    "jalons": [
      8525,
      8531
    ]
  },
  "entite_157": {
    "label": "LOC",
    "text": "|",
    "jalons": [
      8534,
      8535
    ]
  },
  "entite_158": {
    "label": "ORG",
    "text": "Elé",
    "jalons": [
      8560,
      8563
    ]
  },
  "entite_159": {
    "label": "PER",
    "text": "N Il",
    "jalons": [
      8581,
      8585
    ]
  },
  "entite_160": {
    "label": "PER",
    "text": "Eee Ge",
    "jalons": [
      8755,
      8761
    ]
  },
  "entite_161": {
    "label": "LOC",
    "text": "Ge",
    "jalons": [
      8765,
      8767
    ]
  },
  "entite_162": {
    "label": "MISC",
    "text": "A 6",
    "jalons": [
      8771,
      8774
    ]
  },
  "entite_163": {
    "label": "PER",
    "text": "| ETRENNES",
    "jalons": [
      8793,
      8803
    ]
  },
  "entite_164": {
    "label": "MISC",
    "text": "OrME",
    "jalons": [
      8808,
      8812
    ]
  },
  "entite_165": {
    "label": "PER",
    "text": "PAn",
    "jalons": [
      8827,
      8830
    ]
  },
  "entite_166": {
    "label": "PER",
    "text": "Amis",
    "jalons": [
      8872,
      8876
    ]
  },
  "entite_167": {
    "label": "LOC",
    "text": "Lorsqu",
    "jalons": [
      8878,
      8884
    ]
  },
  "entite_168": {
    "label": "PER",
    "text": "D’",
    "jalons": [
      8928,
      8930
    ]
  },
  "entite_169": {
    "label": "ORG",
    "text": "Plume",
    "jalons": [
      8954,
      8959
    ]
  },
  "entite_170": {
    "label": "LOC",
    "text": "Ainff",
    "jalons": [
      8987,
      8992
    ]
  },
  "entite_171": {
    "label": "ORG",
    "text": "Sœurs",
    "jalons": [
      9073,
      9078
    ]
  },
  "entite_172": {
    "label": "LOC",
    "text": "|",
    "jalons": [
      9103,
      9104
    ]
  },
  "entite_173": {
    "label": "LOC",
    "text": "|",
    "jalons": [
      9194,
      9195
    ]
  },
  "entite_174": {
    "label": "LOC",
    "text": "|",
    "jalons": [
      9290,
      9291
    ]
  },
  "entite_175": {
    "label": "PER",
    "text": "Re Got fe Ge",
    "jalons": [
      9292,
      9304
    ]
  },
  "entite_176": {
    "label": "LOC",
    "text": "A MONSIEUR#“*.",
    "jalons": [
      9314,
      9328
    ]
  },
  "entite_177": {
    "label": "LOC",
    "text": "ETRENNES",
    "jalons": [
      9329,
      9337
    ]
  },
  "entite_178": {
    "label": "LOC",
    "text": "|",
    "jalons": [
      9339,
      9340
    ]
  },
  "entite_179": {
    "label": "PER",
    "text": "C E",
    "jalons": [
      9341,
      9344
    ]
  },
  "entite_180": {
    "label": "LOC",
    "text": "les’",
    "jalons": [
      9369,
      9373
    ]
  },
  "entite_181": {
    "label": "MISC",
    "text": "Iris",
    "jalons": [
      9411,
      9415
    ]
  },
  "entite_182": {
    "label": "PER",
    "text": "l’Amant",
    "jalons": [
      9437,
      9444
    ]
  },
  "entite_183": {
    "label": "LOC",
    "text": "Gage",
    "jalons": [
      9455,
      9459
    ]
  },
  "entite_184": {
    "label": "MISC",
    "text": "Baïfer",
    "jalons": [
      9475,
      9481
    ]
  },
  "entite_185": {
    "label": "ORG",
    "text": "les Amis",
    "jalons": [
      9514,
      9522
    ]
  },
  "entite_186": {
    "label": "PER",
    "text": "Apanage",
    "jalons": [
      9548,
      9555
    ]
  },
  "entite_187": {
    "label": "MISC",
    "text": "MERE",
    "jalons": [
      9773,
      9777
    ]
  },
  "entite_188": {
    "label": "ORG",
    "text": "CHA N SON",
    "jalons": [
      9778,
      9787
    ]
  },
  "entite_189": {
    "label": "LOC",
    "text": "Ù",
    "jalons": [
      9793,
      9794
    ]
  },
  "entite_190": {
    "label": "MISC",
    "text": "Printemps de nôtre âde",
    "jalons": [
      9795,
      9817
    ]
  },
  "entite_191": {
    "label": "LOC",
    "text": "|",
    "jalons": [
      9880,
      9881
    ]
  },
  "entite_192": {
    "label": "MISC",
    "text": "Cœur",
    "jalons": [
      9940,
      9944
    ]
  },
  "entite_193": {
    "label": "MISC",
    "text": "Seonspononosoeneaocosser bone ae saateeses",
    "jalons": [
      10085,
      10127
    ]
  },
  "entite_194": {
    "label": "ORG",
    "text": "EPIGRAMME",
    "jalons": [
      10135,
      10144
    ]
  },
  "entite_195": {
    "label": "LOC",
    "text": "Ographie",
    "jalons": [
      10184,
      10192
    ]
  },
  "entite_196": {
    "label": "PER",
    "text": "Léandre",
    "jalons": [
      10217,
      10224
    ]
  },
  "entite_197": {
    "label": "MISC",
    "text": "Portrait juridique & fans fard",
    "jalons": [
      10234,
      10264
    ]
  },
  "entite_198": {
    "label": "PER",
    "text": "Nôtre Adonis",
    "jalons": [
      10320,
      10332
    ]
  },
  "entite_199": {
    "label": "PER",
    "text": "’approchant",
    "jalons": [
      10403,
      10414
    ]
  },
  "entite_200": {
    "label": "MISC",
    "text": "Vôtre Portrait",
    "jalons": [
      10487,
      10501
    ]
  },
  "entite_201": {
    "label": "LOC",
    "text": "Apprenez",
    "jalons": [
      10530,
      10538
    ]
  },
  "entite_202": {
    "label": "MISC",
    "text": "Hero",
    "jalons": [
      10547,
      10551
    ]
  },
  "entite_203": {
    "label": "MISC",
    "text": "Belle à linstant",
    "jalons": [
      10593,
      10609
    ]
  },
  "entite_204": {
    "label": "MISC",
    "text": "RSS BE DH Goo Er",
    "jalons": [
      10612,
      10628
    ]
  },
  "entite_205": {
    "label": "ORG",
    "text": "EPIGRAMME",
    "jalons": [
      10647,
      10656
    ]
  },
  "entite_206": {
    "label": "LOC",
    "text": "faceé Vallon",
    "jalons": [
      10691,
      10703
    ]
  },
  "entite_207": {
    "label": "MISC",
    "text": "Routier tu te targue 5",
    "jalons": [
      10720,
      10742
    ]
  },
  "entite_208": {
    "label": "PER",
    "text": "Tes Ecrits",
    "jalons": [
      10746,
      10756
    ]
  },
  "entite_209": {
    "label": "PER",
    "text": "’ Apollon",
    "jalons": [
      10776,
      10785
    ]
  },
  "entite_210": {
    "label": "MISC",
    "text": "Critique",
    "jalons": [
      10887,
      10895
    ]
  },
  "entite_211": {
    "label": "MISC",
    "text": "Dieu",
    "jalons": [
      10977,
      10981
    ]
  },
  "entite_212": {
    "label": "MISC",
    "text": "En\n\nLû & approuvé",
    "jalons": [
      11066,
      11083
    ]
  },
  "entite_213": {
    "label": "PER",
    "text": "Mars",
    "jalons": [
      11098,
      11102
    ]
  },
  "entite_214": {
    "label": "MISC",
    "text": "C REBELLION",
    "jalons": [
      11109,
      11120
    ]
  },
  "entite_215": {
    "label": "ORG",
    "text": "MARVILLE",
    "jalons": [
      11219,
      11227
    ]
  },
  "entite_216": {
    "label": "MISC",
    "text": "Der Inpéet",
    "jalons": [
      11239,
      11249
    ]
  },
  "entite_217": {
    "label": "MISC",
    "text": "J",
    "jalons": [
      11253,
      11254
    ]
  },
  "entite_218": {
    "label": "MISC",
    "text": "LAmes Bj Ponts",
    "jalons": [
      11255,
      11269
    ]
  },
  "entite_219": {
    "label": "LOC",
    "text": "Line NAN É\n\n",
    "jalons": [
      11283,
      11295
    ]
  }
}