{
  "voc_eval_res": {
    "precision": 45.3125,
    "recall": 13.3028,
    "f-score": 20.5674
  },
  "KL_res": {
    "KL divergence": 3.543652771325707,
    "Euclidean Dist.": 0.25675362038508337,
    "WER": 0.8035087719298246,
    "CER": 0.6002532714225411,
    "Cosine Dist.": 0.19966617472446868
  },
  "occ_eval_res": {
    "precision": 40.678,
    "recall": 25.2632,
    "f-score": 31.1688
  },
  "clean_eval": {
    "f-score": 18.433179723502302,
    "precision": 15.56420233463035,
    "recall": 22.598870056497177,
    "tp": 40,
    "fp": 217,
    "fn": 137
  },
  "jaccard": [
    0.6870789957134109
  ],
  "braycurtis": [
    0.4039301310043668
  ],
  "dice": [
    0.523320895522388
  ],
  "cosinus": [
    0.16548112796826808
  ]
}