{
  "spacy-lg-3.5.1_kraken4.3.13.dev25": {
    "EN-occ": 3247,
    "EN-type": 2400
  },
  "spacy-lg-3.5.1_lectaurep-kraken4.3.13.dev25": {
    "EN-occ": 4522,
    "EN-type": 3771
  },
  "spacy-lg-3.5.1_tesseract0.3.10": {
    "EN-occ": 980,
    "EN-type": 391
  },
  "spacy-lg-3.5.1_TesseractFra-PNG": {
    "EN-occ": 1055,
    "EN-type": 577
  },
  "spacy-lg-3.5.1_kraken": {
    "EN-occ": 1022,
    "EN-type": 546
  },
  "spacy-lg-3.5.1_Ref": {
    "EN-occ": 646,
    "EN-type": 171
  },
  "spacy-md-3.5.1_kraken4.3.13.dev25": {
    "EN-occ": 3059,
    "EN-type": 2221
  },
  "spacy-md-3.5.1_lectaurep-kraken4.3.13.dev25": {
    "EN-occ": 3639,
    "EN-type": 3018
  },
  "spacy-md-3.5.1_tesseract0.3.10": {
    "EN-occ": 948,
    "EN-type": 411
  },
  "spacy-md-3.5.1_TesseractFra-PNG": {
    "EN-occ": 785,
    "EN-type": 448
  },
  "spacy-md-3.5.1_kraken": {
    "EN-occ": 885,
    "EN-type": 484
  },
  "spacy-md-3.5.1_Ref": {
    "EN-occ": 866,
    "EN-type": 189
  },
  "spacy-sm-3.5.1_kraken4.3.13.dev25": {
    "EN-occ": 3093,
    "EN-type": 2176
  },
  "spacy-sm-3.5.1_lectaurep-kraken4.3.13.dev25": {
    "EN-occ": 3220,
    "EN-type": 2640
  },
  "spacy-sm-3.5.1_tesseract0.3.10": {
    "EN-occ": 1347,
    "EN-type": 471
  },
  "spacy-sm-3.5.1_TesseractFra-PNG": {
    "EN-occ": 2109,
    "EN-type": 757
  },
  "spacy-sm-3.5.1_kraken": {
    "EN-occ": 968,
    "EN-type": 467
  },
  "spacy-sm-3.5.1_Ref": {
    "EN-occ": 1002,
    "EN-type": 275
  }
}