{
  "spacy-lg-3.5.1_kraken4.3.13.dev25-jspll-ELTeC": {
    "EN-occ": 1191,
    "EN-type": 866
  },
  "spacy-lg-3.5.1_kraken4.3.13.dev25-jspll-pretrain": {
    "EN-occ": 1067,
    "EN-type": 690
  },
  "spacy-lg-3.5.1_kraken4.3.13.dev25": {
    "EN-occ": 1363,
    "EN-type": 930
  },
  "spacy-lg-3.5.1_lectaurep-kraken4.3.13.dev25-jspll-ELTeC": {
    "EN-occ": 1617,
    "EN-type": 1264
  },
  "spacy-lg-3.5.1_lectaurep-kraken4.3.13.dev25-jspll-pretrain": {
    "EN-occ": 1348,
    "EN-type": 968
  },
  "spacy-lg-3.5.1_lectaurep-kraken4.3.13.dev25": {
    "EN-occ": 1769,
    "EN-type": 1306
  },
  "spacy-lg-3.5.1_tesseract0.3.10-jspll-ELTeC": {
    "EN-occ": 328,
    "EN-type": 185
  },
  "spacy-lg-3.5.1_tesseract0.3.10-jspll-pretrain": {
    "EN-occ": 363,
    "EN-type": 201
  },
  "spacy-lg-3.5.1_tesseract0.3.10": {
    "EN-occ": 373,
    "EN-type": 203
  },
  "spacy-lg-3.5.1_Ref": {
    "EN-occ": 213,
    "EN-type": 71
  },
  "spacy-md-3.5.1_kraken4.3.13.dev25-jspll-ELTeC": {
    "EN-occ": 1095,
    "EN-type": 771
  },
  "spacy-md-3.5.1_kraken4.3.13.dev25-jspll-pretrain": {
    "EN-occ": 1046,
    "EN-type": 657
  },
  "spacy-md-3.5.1_kraken4.3.13.dev25": {
    "EN-occ": 1241,
    "EN-type": 839
  },
  "spacy-md-3.5.1_lectaurep-kraken4.3.13.dev25-jspll-ELTeC": {
    "EN-occ": 1394,
    "EN-type": 1078
  },
  "spacy-md-3.5.1_lectaurep-kraken4.3.13.dev25-jspll-pretrain": {
    "EN-occ": 1298,
    "EN-type": 940
  },
  "spacy-md-3.5.1_lectaurep-kraken4.3.13.dev25": {
    "EN-occ": 1550,
    "EN-type": 1116
  },
  "spacy-md-3.5.1_tesseract0.3.10-jspll-ELTeC": {
    "EN-occ": 368,
    "EN-type": 206
  },
  "spacy-md-3.5.1_tesseract0.3.10-jspll-pretrain": {
    "EN-occ": 381,
    "EN-type": 194
  },
  "spacy-md-3.5.1_tesseract0.3.10": {
    "EN-occ": 371,
    "EN-type": 187
  },
  "spacy-md-3.5.1_Ref": {
    "EN-occ": 231,
    "EN-type": 74
  },
  "spacy-sm-3.5.1_kraken4.3.13.dev25-jspll-ELTeC": {
    "EN-occ": 1261,
    "EN-type": 858
  },
  "spacy-sm-3.5.1_kraken4.3.13.dev25-jspll-pretrain": {
    "EN-occ": 1265,
    "EN-type": 799
  },
  "spacy-sm-3.5.1_kraken4.3.13.dev25": {
    "EN-occ": 1414,
    "EN-type": 921
  },
  "spacy-sm-3.5.1_lectaurep-kraken4.3.13.dev25-jspll-ELTeC": {
    "EN-occ": 1470,
    "EN-type": 1099
  },
  "spacy-sm-3.5.1_lectaurep-kraken4.3.13.dev25-jspll-pretrain": {
    "EN-occ": 1477,
    "EN-type": 1010
  },
  "spacy-sm-3.5.1_lectaurep-kraken4.3.13.dev25": {
    "EN-occ": 1713,
    "EN-type": 1193
  },
  "spacy-sm-3.5.1_tesseract0.3.10-jspll-ELTeC": {
    "EN-occ": 585,
    "EN-type": 259
  },
  "spacy-sm-3.5.1_tesseract0.3.10-jspll-pretrain": {
    "EN-occ": 627,
    "EN-type": 286
  },
  "spacy-sm-3.5.1_tesseract0.3.10": {
    "EN-occ": 656,
    "EN-type": 294
  },
  "spacy-sm-3.5.1_Ref": {
    "EN-occ": 295,
    "EN-type": 116
  }
}