{
  "entite_0": {
    "label": "MISC",
    "text": "Érivières",
    "jalons": [
      30,
      39
    ]
  },
  "entite_1": {
    "label": "PER",
    "text": "Bernard\nBonafoux",
    "jalons": [
      78,
      94
    ]
  },
  "entite_2": {
    "label": "MISC",
    "text": "Source gallica.bnf.fr /",
    "jalons": [
      99,
      122
    ]
  },
  "entite_3": {
    "label": "LOC",
    "text": "Bibliothèque nationale de France\n\f\n11 Gallica\n\n \n\nBonafoux",
    "jalons": [
      123,
      181
    ]
  },
  "entite_4": {
    "label": "MISC",
    "text": "Bernard",
    "jalons": [
      183,
      190
    ]
  },
  "entite_5": {
    "label": "MISC",
    "text": "Érivières",
    "jalons": [
      223,
      232
    ]
  },
  "entite_6": {
    "label": "PER",
    "text": "Bernard Bonafoux",
    "jalons": [
      271,
      287
    ]
  },
  "entite_7": {
    "label": "MISC",
    "text": "Gallica",
    "jalons": [
      340,
      347
    ]
  },
  "entite_8": {
    "label": "MISC",
    "text": "BnF. Leur réutilisation",
    "jalons": [
      471,
      494
    ]
  },
  "entite_9": {
    "label": "LOC",
    "text": "Bibliothèque nationale de France",
    "jalons": [
      859,
      891
    ]
  },
  "entite_10": {
    "label": "ORG",
    "text": "BnF",
    "jalons": [
      923,
      926
    ]
  },
  "entite_11": {
    "label": "MISC",
    "text": "AUX TARIFS ET",
    "jalons": [
      1449,
      1462
    ]
  },
  "entite_12": {
    "label": "MISC",
    "text": "LICENCE\n\n \n\n",
    "jalons": [
      1468,
      1480
    ]
  },
  "entite_13": {
    "label": "MISC",
    "text": "Gallica",
    "jalons": [
      1499,
      1506
    ]
  },
  "entite_14": {
    "label": "ORG",
    "text": "BnF",
    "jalons": [
      1531,
      1534
    ]
  },
  "entite_15": {
    "label": "ORG",
    "text": "L.2112-1",
    "jalons": [
      1556,
      1564
    ]
  },
  "entite_16": {
    "label": "ORG",
    "text": "Source gallica.BnF.fr / Bibliothèque municipale de …",
    "jalons": [
      2075,
      2127
    ]
  },
  "entite_17": {
    "label": "MISC",
    "text": "Gallica",
    "jalons": [
      2259,
      2266
    ]
  },
  "entite_18": {
    "label": "ORG",
    "text": "BnF",
    "jalons": [
      2306,
      2309
    ]
  },
  "entite_19": {
    "label": "MISC",
    "text": "Gallica",
    "jalons": [
      2477,
      2484
    ]
  },
  "entite_20": {
    "label": "MISC",
    "text": "Gallica",
    "jalons": [
      2988,
      2995
    ]
  },
  "entite_21": {
    "label": "MISC",
    "text": "BERNARD",
    "jalons": [
      3065,
      3072
    ]
  },
  "entite_22": {
    "label": "MISC",
    "text": "BONAFOUX",
    "jalons": [
      3073,
      3081
    ]
  },
  "entite_23": {
    "label": "LOC",
    "text": "Poëles",
    "jalons": [
      3095,
      3101
    ]
  },
  "entite_24": {
    "label": "MISC",
    "text": "NOUVELLES",
    "jalons": [
      3110,
      3119
    ]
  },
  "entite_25": {
    "label": "MISC",
    "text": "CONTRE",
    "jalons": [
      3128,
      3134
    ]
  },
  "entite_26": {
    "label": "ORG",
    "text": "INPIÉTÉ\n\nPrix : 50 Cent",
    "jalons": [
      3137,
      3160
    ]
  },
  "entite_27": {
    "label": "MISC",
    "text": "EN VENTE\n\nL CHEZ MARIUS VIDAL",
    "jalons": [
      3163,
      3192
    ]
  },
  "entite_28": {
    "label": "LOC",
    "text": "Brignoles",
    "jalons": [
      3230,
      3239
    ]
  },
  "entite_29": {
    "label": "MISC",
    "text": "RSS",
    "jalons": [
      3262,
      3265
    ]
  },
  "entite_30": {
    "label": "PER",
    "text": "DU MÊME AUTEUR\n\nDE",
    "jalons": [
      3299,
      3317
    ]
  },
  "entite_31": {
    "label": "MISC",
    "text": "Les Sonnets de Provence",
    "jalons": [
      3321,
      3344
    ]
  },
  "entite_32": {
    "label": "PER",
    "text": "André Expirer",
    "jalons": [
      3362,
      3375
    ]
  },
  "entite_33": {
    "label": "LOC",
    "text": "rue Vivienne",
    "jalons": [
      3377,
      3389
    ]
  },
  "entite_34": {
    "label": "LOC",
    "text": "Paris",
    "jalons": [
      3394,
      3399
    ]
  },
  "entite_35": {
    "label": "LOC",
    "text": "Érivières",
    "jalons": [
      3406,
      3415
    ]
  },
  "entite_36": {
    "label": "PER",
    "text": "Marius Einar",
    "jalons": [
      3431,
      3443
    ]
  },
  "entite_37": {
    "label": "LOC",
    "text": "Brignoles",
    "jalons": [
      3447,
      3456
    ]
  },
  "entite_38": {
    "label": "MISC",
    "text": "Les Joies et les Larmes",
    "jalons": [
      3483,
      3506
    ]
  },
  "entite_39": {
    "label": "MISC",
    "text": "Cruche à l'Eau",
    "jalons": [
      3550,
      3564
    ]
  },
  "entite_40": {
    "label": "MISC",
    "text": "Les Dupes d'eux-mêmes",
    "jalons": [
      3596,
      3617
    ]
  },
  "entite_41": {
    "label": "MISC",
    "text": "Le Retour",
    "jalons": [
      3648,
      3657
    ]
  },
  "entite_42": {
    "label": "LOC",
    "text": "um mé Smet",
    "jalons": [
      3697,
      3707
    ]
  },
  "entite_43": {
    "label": "LOC",
    "text": "us",
    "jalons": [
      3735,
      3737
    ]
  },
  "entite_44": {
    "label": "LOC",
    "text": "LES",
    "jalons": [
      3745,
      3748
    ]
  },
  "entite_45": {
    "label": "MISC",
    "text": "NouveLLes PAIRES CONTRE L']MPIÉTÉ\n\nPAR",
    "jalons": [
      3774,
      3812
    ]
  },
  "entite_46": {
    "label": "LOC",
    "text": "BERNARD BONAFOUX",
    "jalons": [
      3814,
      3830
    ]
  },
  "entite_47": {
    "label": "MISC",
    "text": "Ça",
    "jalons": [
      4136,
      4138
    ]
  },
  "entite_48": {
    "label": "MISC",
    "text": "Si",
    "jalons": [
      4235,
      4237
    ]
  },
  "entite_49": {
    "label": "MISC",
    "text": "De vous je pense être entendu",
    "jalons": [
      4270,
      4299
    ]
  },
  "entite_50": {
    "label": "MISC",
    "text": "Et je suis ce que",
    "jalons": [
      4551,
      4568
    ]
  },
  "entite_51": {
    "label": "MISC",
    "text": "Dieu",
    "jalons": [
      4569,
      4573
    ]
  },
  "entite_52": {
    "label": "MISC",
    "text": "Dieu",
    "jalons": [
      4588,
      4592
    ]
  },
  "entite_53": {
    "label": "PER",
    "text": "Père",
    "jalons": [
      4611,
      4615
    ]
  },
  "entite_54": {
    "label": "MISC",
    "text": "Car ma louange part du cœur",
    "jalons": [
      4802,
      4829
    ]
  },
  "entite_55": {
    "label": "LOC",
    "text": "fo",
    "jalons": [
      4847,
      4849
    ]
  },
  "entite_56": {
    "label": "MISC",
    "text": "LES RICHES EN ESPRIT",
    "jalons": [
      4893,
      4913
    ]
  },
  "entite_57": {
    "label": "MISC",
    "text": "Nous sommes",
    "jalons": [
      4967,
      4978
    ]
  },
  "entite_58": {
    "label": "MISC",
    "text": "Nous redoutons l’enfer",
    "jalons": [
      5017,
      5039
    ]
  },
  "entite_59": {
    "label": "MISC",
    "text": "Nous évitons",
    "jalons": [
      5068,
      5080
    ]
  },
  "entite_60": {
    "label": "MISC",
    "text": "Du bon et vieux curé",
    "jalons": [
      5116,
      5136
    ]
  },
  "entite_61": {
    "label": "MISC",
    "text": "Notre âme",
    "jalons": [
      5436,
      5445
    ]
  },
  "entite_62": {
    "label": "PER",
    "text": "Montrez",
    "jalons": [
      5705,
      5712
    ]
  },
  "entite_63": {
    "label": "MISC",
    "text": "Dieu",
    "jalons": [
      5823,
      5827
    ]
  },
  "entite_64": {
    "label": "MISC",
    "text": "Allons, beaux généreux",
    "jalons": [
      5980,
      6002
    ]
  },
  "entite_65": {
    "label": "MISC",
    "text": "Tendez",
    "jalons": [
      6075,
      6081
    ]
  },
  "entite_66": {
    "label": "PER",
    "text": "Pascal",
    "jalons": [
      6142,
      6148
    ]
  },
  "entite_67": {
    "label": "PER",
    "text": "Bacon",
    "jalons": [
      6150,
      6155
    ]
  },
  "entite_68": {
    "label": "PER",
    "text": "Chateaubriand",
    "jalons": [
      6157,
      6170
    ]
  },
  "entite_69": {
    "label": "MISC",
    "text": "Oh !",
    "jalons": [
      6405,
      6409
    ]
  },
  "entite_70": {
    "label": "MISC",
    "text": "Vous faites noblement emploi de vos richesses",
    "jalons": [
      6455,
      6500
    ]
  },
  "entite_71": {
    "label": "PER",
    "text": "Arouet",
    "jalons": [
      6514,
      6520
    ]
  },
  "entite_72": {
    "label": "PER",
    "text": "Gorgias",
    "jalons": [
      6556,
      6563
    ]
  },
  "entite_73": {
    "label": "PER",
    "text": "Soit",
    "jalons": [
      6590,
      6594
    ]
  },
  "entite_74": {
    "label": "MISC",
    "text": "Un vase qui jamais",
    "jalons": [
      6642,
      6660
    ]
  },
  "entite_75": {
    "label": "LOC",
    "text": "Sèvres",
    "jalons": [
      6809,
      6815
    ]
  },
  "entite_76": {
    "label": "LOC",
    "text": "N'",
    "jalons": [
      6817,
      6819
    ]
  },
  "entite_77": {
    "label": "PER",
    "text": "Voltaire",
    "jalons": [
      6870,
      6878
    ]
  },
  "entite_78": {
    "label": "MISC",
    "text": "Dieu",
    "jalons": [
      6963,
      6967
    ]
  },
  "entite_79": {
    "label": "PER",
    "text": "Arouet",
    "jalons": [
      6969,
      6975
    ]
  },
  "entite_80": {
    "label": "MISC",
    "text": "Dieu",
    "jalons": [
      7056,
      7060
    ]
  },
  "entite_81": {
    "label": "MISC",
    "text": "Panini",
    "jalons": [
      7223,
      7229
    ]
  },
  "entite_82": {
    "label": "PER",
    "text": "Julien",
    "jalons": [
      7234,
      7240
    ]
  },
  "entite_83": {
    "label": "PER",
    "text": "M. Tronchin",
    "jalons": [
      7331,
      7342
    ]
  },
  "entite_84": {
    "label": "MISC",
    "text": "Dictionnaire Historique",
    "jalons": [
      7453,
      7476
    ]
  },
  "entite_85": {
    "label": "LOC",
    "text": "Augsbourg",
    "jalons": [
      7478,
      7487
    ]
  },
  "entite_86": {
    "label": "PER",
    "text": "Crésus",
    "jalons": [
      7585,
      7591
    ]
  },
  "entite_87": {
    "label": "MISC",
    "text": "De très-près",
    "jalons": [
      7614,
      7626
    ]
  },
  "entite_88": {
    "label": "MISC",
    "text": "L GORE AD recueil",
    "jalons": [
      7727,
      7744
    ]
  },
  "entite_89": {
    "label": "MISC",
    "text": "HYPOCRITES\n\nDE L'ATHÉISME\n\n \n\nL'",
    "jalons": [
      7826,
      7858
    ]
  },
  "entite_90": {
    "label": "MISC",
    "text": "Dieu",
    "jalons": [
      7958,
      7962
    ]
  },
  "entite_91": {
    "label": "MISC",
    "text": "Dieu",
    "jalons": [
      8164,
      8168
    ]
  },
  "entite_92": {
    "label": "LOC",
    "text": "F",
    "jalons": [
      8173,
      8174
    ]
  },
  "entite_93": {
    "label": "MISC",
    "text": "X. DernIer",
    "jalons": [
      8176,
      8186
    ]
  },
  "entite_94": {
    "label": "MISC",
    "text": "Dieu",
    "jalons": [
      8210,
      8214
    ]
  },
  "entite_95": {
    "label": "MISC",
    "text": "Vous osez l'avouer ici",
    "jalons": [
      8244,
      8266
    ]
  },
  "entite_96": {
    "label": "LOC",
    "text": "Très-Haut",
    "jalons": [
      8445,
      8454
    ]
  },
  "entite_97": {
    "label": "MISC",
    "text": "D'autres",
    "jalons": [
      8474,
      8482
    ]
  },
  "entite_98": {
    "label": "MISC",
    "text": "Ni le peuple",
    "jalons": [
      8529,
      8541
    ]
  },
  "entite_99": {
    "label": "PER",
    "text": "Roi",
    "jalons": [
      8569,
      8572
    ]
  },
  "entite_100": {
    "label": "MISC",
    "text": "En saluant la mort d’un gracieux sourire",
    "jalons": [
      8623,
      8663
    ]
  },
  "entite_101": {
    "label": "MISC",
    "text": "Fatale illusion !",
    "jalons": [
      8667,
      8684
    ]
  },
  "entite_102": {
    "label": "PER",
    "text": "Faute",
    "jalons": [
      8873,
      8878
    ]
  },
  "entite_103": {
    "label": "MISC",
    "text": "Vous aurez le néant à l’heure du trépas",
    "jalons": [
      8968,
      9007
    ]
  },
  "entite_104": {
    "label": "MISC",
    "text": "Pauvre mystifié!",
    "jalons": [
      9010,
      9026
    ]
  },
  "entite_105": {
    "label": "MISC",
    "text": "Couronnement béni de tous vos sacrifices",
    "jalons": [
      9049,
      9089
    ]
  },
  "entite_106": {
    "label": "MISC",
    "text": "Vous êtes un enfant",
    "jalons": [
      9216,
      9235
    ]
  },
  "entite_107": {
    "label": "MISC",
    "text": "Comme l'oiseau du ciel j'aime ma liberté",
    "jalons": [
      9304,
      9344
    ]
  },
  "entite_108": {
    "label": "MISC",
    "text": "Je vais sans nul souci",
    "jalons": [
      9540,
      9562
    ]
  },
  "entite_109": {
    "label": "MISC",
    "text": "Me",
    "jalons": [
      9636,
      9638
    ]
  },
  "entite_110": {
    "label": "MISC",
    "text": "Votre Dieu",
    "jalons": [
      10135,
      10145
    ]
  },
  "entite_111": {
    "label": "MISC",
    "text": "TITI\n\nCet étrange discours",
    "jalons": [
      10227,
      10253
    ]
  },
  "entite_112": {
    "label": "MISC",
    "text": "Provoqua",
    "jalons": [
      10278,
      10286
    ]
  },
  "entite_113": {
    "label": "MISC",
    "text": "Aux amis accoudés sur une table ronde",
    "jalons": [
      10370,
      10407
    ]
  },
  "entite_114": {
    "label": "MISC",
    "text": "Dieu grand",
    "jalons": [
      10632,
      10642
    ]
  },
  "entite_115": {
    "label": "LOC",
    "text": "Beaux",
    "jalons": [
      10974,
      10979
    ]
  },
  "entite_116": {
    "label": "LOC",
    "text": "A",
    "jalons": [
      11134,
      11135
    ]
  },
  "entite_117": {
    "label": "MISC",
    "text": "Rende la douce joie et le bonheur suprême",
    "jalons": [
      11324,
      11365
    ]
  },
  "entite_118": {
    "label": "MISC",
    "text": "Voilà pour un.",
    "jalons": [
      11501,
      11515
    ]
  },
  "entite_119": {
    "label": "MISC",
    "text": "Espérant",
    "jalons": [
      11908,
      11916
    ]
  },
  "entite_120": {
    "label": "MISC",
    "text": "Vous êtes confondus!",
    "jalons": [
      11994,
      12014
    ]
  },
  "entite_121": {
    "label": "MISC",
    "text": "Écoutez",
    "jalons": [
      12015,
      12022
    ]
  },
  "entite_122": {
    "label": "MISC",
    "text": "Mes récits indiscrets",
    "jalons": [
      12035,
      12056
    ]
  },
  "entite_123": {
    "label": "MISC",
    "text": "Créateur",
    "jalons": [
      12361,
      12369
    ]
  },
  "entite_124": {
    "label": "MISC",
    "text": "Escalade nus",
    "jalons": [
      12490,
      12502
    ]
  },
  "entite_125": {
    "label": "MISC",
    "text": "Parlez",
    "jalons": [
      12553,
      12559
    ]
  },
  "entite_126": {
    "label": "MISC",
    "text": "Dirent",
    "jalons": [
      12582,
      12588
    ]
  },
  "entite_127": {
    "label": "MISC",
    "text": "CONVOI FUNÉÈBRE",
    "jalons": [
      12770,
      12785
    ]
  },
  "entite_128": {
    "label": "MISC",
    "text": "Un mort",
    "jalons": [
      12886,
      12893
    ]
  },
  "entite_129": {
    "label": "MISC",
    "text": "À su chrétiennement",
    "jalons": [
      12935,
      12954
    ]
  },
  "entite_130": {
    "label": "MISC",
    "text": "Dieu",
    "jalons": [
      12972,
      12976
    ]
  },
  "entite_131": {
    "label": "MISC",
    "text": "Qu'on doit se réunir",
    "jalons": [
      13028,
      13048
    ]
  },
  "entite_132": {
    "label": "PER",
    "text": "Quelques De Profundis",
    "jalons": [
      13247,
      13268
    ]
  },
  "entite_133": {
    "label": "MISC",
    "text": "Que je sois un dévot",
    "jalons": [
      13291,
      13311
    ]
  },
  "entite_134": {
    "label": "MISC",
    "text": "Sacrement\n\nS'il s’en va tout muni",
    "jalons": [
      13324,
      13357
    ]
  },
  "entite_135": {
    "label": "MISC",
    "text": "Qu'il a reçu là-haut",
    "jalons": [
      13384,
      13404
    ]
  },
  "entite_136": {
    "label": "MISC",
    "text": "Les soi-disant amis",
    "jalons": [
      13520,
      13539
    ]
  },
  "entite_137": {
    "label": "MISC",
    "text": "Suivant le sarcophage avec indifférence",
    "jalons": [
      13566,
      13605
    ]
  },
  "entite_138": {
    "label": "PER",
    "text": "Périrent",
    "jalons": [
      13609,
      13617
    ]
  },
  "entite_139": {
    "label": "ORG",
    "text": "coup-d’œil",
    "jalons": [
      13675,
      13685
    ]
  },
  "entite_140": {
    "label": "ORG",
    "text": "Académie",
    "jalons": [
      13975,
      13983
    ]
  },
  "entite_141": {
    "label": "MISC",
    "text": "Voilà les entretiens d’un funèbre convoi!\n\nBien",
    "jalons": [
      14272,
      14319
    ]
  },
  "entite_142": {
    "label": "MISC",
    "text": "Que l'on n'y pense plus!",
    "jalons": [
      14449,
      14473
    ]
  },
  "entite_143": {
    "label": "LOC",
    "text": "Atteindront",
    "jalons": [
      14732,
      14743
    ]
  },
  "entite_144": {
    "label": "MISC",
    "text": "Qu'ils prient pour les morts",
    "jalons": [
      14981,
      15009
    ]
  },
  "entite_145": {
    "label": "MISC",
    "text": "Évitant l’eau bénite et l'odeur de l’encens",
    "jalons": [
      15039,
      15082
    ]
  },
  "entite_146": {
    "label": "MISC",
    "text": "Oh!",
    "jalons": [
      15230,
      15233
    ]
  },
  "entite_147": {
    "label": "MISC",
    "text": "Dieu",
    "jalons": [
      15783,
      15787
    ]
  },
  "entite_148": {
    "label": "PER",
    "text": "N",
    "jalons": [
      15862,
      15863
    ]
  },
  "entite_149": {
    "label": "MISC",
    "text": "À Certains Critiques",
    "jalons": [
      15872,
      15892
    ]
  },
  "entite_150": {
    "label": "MISC",
    "text": "Ée",
    "jalons": [
      15909,
      15911
    ]
  },
  "entite_151": {
    "label": "MISC",
    "text": "Les Riches en Esprit",
    "jalons": [
      15917,
      15937
    ]
  },
  "entite_152": {
    "label": "MISC",
    "text": "Les Hypocrites de l'Athéisme",
    "jalons": [
      15943,
      15971
    ]
  },
  "entite_153": {
    "label": "MISC",
    "text": "Le Convoi Funèbre",
    "jalons": [
      15991,
      16008
    ]
  },
  "entite_154": {
    "label": "MISC",
    "text": "Une Forte Tête",
    "jalons": [
      16037,
      16051
    ]
  },
  "entite_155": {
    "label": "LOC",
    "text": "Typographie de A. VIAN",
    "jalons": [
      16101,
      16123
    ]
  },
  "entite_156": {
    "label": "LOC",
    "text": "Portail-Neuf",
    "jalons": [
      16133,
      16145
    ]
  },
  "entite_157": {
    "label": "LOC",
    "text": "N",
    "jalons": [
      16147,
      16148
    ]
  },
  "entite_158": {
    "label": "LOC",
    "text": "A7",
    "jalons": [
      16163,
      16165
    ]
  },
  "entite_159": {
    "label": "MISC",
    "text": "Ms",
    "jalons": [
      16172,
      16174
    ]
  },
  "entite_160": {
    "label": "ORG",
    "text": "NÔNE",
    "jalons": [
      16232,
      16236
    ]
  },
  "entite_161": {
    "label": "LOC",
    "text": "Livres",
    "jalons": [
      16282,
      16288
    ]
  },
  "entite_162": {
    "label": "PER",
    "text": "Piété",
    "jalons": [
      16294,
      16299
    ]
  },
  "entite_163": {
    "label": "MISC",
    "text": "Cartes Géographiques",
    "jalons": [
      16303,
      16323
    ]
  },
  "entite_164": {
    "label": "MISC",
    "text": "Gravures et Encadrements artistiques",
    "jalons": [
      16328,
      16364
    ]
  },
  "entite_165": {
    "label": "MISC",
    "text": "Religion",
    "jalons": [
      16377,
      16385
    ]
  }
}